{"version_list": [{"name": "『空月之歌·复演』回望湮灭的月光", "code": "月之二", "banner": "https://sdk-webstatic.mihoyo.com/upload/ann/2025/09/28/23c0eae0f4d2cb5393e739ed616b7a20_2082241063911125600_transformed.jpg", "start_time": "2025-10-22T11:00:00", "end_time": "2025-12-03T06:00:00", "sp_time": null, "ann_list": [{"id": 21364, "title": "「解探月域，琢炼宵晖」活动：新手自选邀约「奔行世间」常驻祈愿5星角色", "description": "「解探月域，琢炼宵晖」", "game": "原神", "start_time": "2025-10-22T11:00:00", "end_time": "2026-08-12T05:59:00", "banner": "https://sdk-webstatic.mihoyo.com/upload/ann/2025/10/10/c37b7eb5cb7dcb7dafcc5273797fd124_7132926859369047800_transformed.jpg", "ann_type": "event"}, {"id": 21325, "title": "「砺行修远」：勤修馈赠", "description": "「砺行修远」", "game": "原神", "start_time": "2025-09-08T12:00:00", "end_time": "2025-12-01T03:59:00", "banner": "https://sdk-webstatic.mihoyo.com/upload/ann/2025/09/01/9d9818e0badc0b90e9c6d7e10a9023ce_3429418709384054143_transformed.png", "ann_type": "event"}, {"id": 21284, "title": "「冷月逸照的乐屿」时限内完成探索任务，可额外获得原石*400奖励", "description": "「冷月逸照的乐屿」", "game": "原神", "start_time": "2025-09-08T12:00:00", "end_time": "2025-12-02T14:59:59", "banner": "https://sdk-webstatic.mihoyo.com/upload/ann/2025/08/28/a2ae314f760bb0b5de76de4a097ee19e_5468588135090445069_transformed.png", "ann_type": "event"}, {"id": 21168, "title": "「幽境危战」活动：紊乱地脉挑战", "description": "「幽境危战」", "game": "原神", "start_time": "2025-10-29T10:00:00", "end_time": "2025-12-02T03:59:59", "banner": "https://sdk-webstatic.mihoyo.com/upload/ann/2025/10/23/d030bb81196ef3fff410d9f9c4d6120d_5245917935282258365_transformed.jpg", "ann_type": "event"}, {"id": 21367, "title": "「参究故墟·稳健知行」活动：参与邀请「萃念初蘖·柯莱(草)」", "description": "「参究故墟·稳健知行」", "game": "原神", "start_time": "2025-11-07T10:00:00", "end_time": "2025-11-24T03:59:59", "banner": "https://sdk-webstatic.mihoyo.com/upload/ann/2025/10/10/8fa94321598eb241cc9bccd8ddb766c6_4365695750030147451_transformed.jpg", "ann_type": "event"}, {"id": 21369, "title": "「炉边烬影」角色祈愿: 阿蕾奇诺", "description": "「炉边烬影」祈愿", "game": "原神", "start_time": "2025-11-11T18:00:00", "end_time": "2025-12-02T14:59:59", "banner": "https://sdk-webstatic.mihoyo.com/upload/ann/2025/10/27/2f111d98ed1546622723926ccf2390ff_6846678039903189647_transformed.jpg", "ann_type": "gacha"}, {"id": 21370, "title": "「陵薮市朝」角色祈愿: 钟离", "description": "「陵薮市朝」祈愿", "game": "原神", "start_time": "2025-11-11T18:00:00", "end_time": "2025-12-02T14:59:59", "banner": "https://sdk-webstatic.mihoyo.com/upload/ann/2025/10/30/9b8fd1a3f0253522e88257b5e41a01bf_2818543260027643242_transformed.jpg", "ann_type": "gacha"}, {"id": 21371, "title": "「神铸赋形」武器祈愿: 赤月之形, 贯虹之槊", "description": "「神铸赋形」祈愿", "game": "原神", "start_time": "2025-11-11T18:00:00", "end_time": "2025-12-02T14:59:59", "banner": "https://sdk-webstatic.mihoyo.com/upload/ann/2025/10/27/54cde6bd8912354aa5b358d42a69dd79_6997260099594855541_transformed.jpg", "ann_type": "gacha"}]}]}